{"src/test/java/features/SAAS_Functional_TCs_Web Automation_SRS_TestCases_202306210730591.feature:31":{"file_name":"src/test/java/features/SAAS_Functional_TCs_Web Automation_SRS_TestCases_202306210730591.feature","location":{"line":1,"column":1},"feature_name":"SAAS_Functional_TCs_Web Automation_SRS_TestCases_202306210730591","scenario_name":"Creating an Account","scenario_location":{"line":12,"column":1},"steps":[{"type":"Step","location":{"line":13,"column":1},"keyword":"Given ","text":"I have access to application"},{"type":"Step","location":{"line":14,"column":1},"keyword":"When ","text":"I selected Sign Up link in sign up"},{"type":"Step","location":{"line":15,"column":1},"keyword":"Then ","text":"verify displayed Sign Up to AlgoShack in sign up"},{"type":"Step","location":{"line":16,"column":1},"keyword":"When ","text":"I entered First Name in sign up as '<First Name>'"},{"type":"Step","location":{"line":17,"column":1},"keyword":"And ","text":"I entered Last Name in sign up as '<Last Name>'"},{"type":"Step","location":{"line":18,"column":1},"keyword":"And ","text":"I entered Email Addresss in sign up as '<Email Addresss>'"},{"type":"Step","location":{"line":19,"column":1},"keyword":"And ","text":"I entered Passwords in sign up as '<Passwords>'"},{"type":"Step","location":{"line":20,"column":1},"keyword":"And ","text":"I entered Confirm Password in sign up as '<Confirm Password>'"},{"type":"Step","location":{"line":21,"column":1},"keyword":"And ","text":"I selected Are you a in sign up"},{"type":"Step","location":{"line":22,"column":1},"keyword":"And ","text":"I selected Student in sign up"},{"type":"Step","location":{"line":23,"column":1},"keyword":"And ","text":"I checked Terms And Agreement in sign up"},{"type":"Step","location":{"line":24,"column":1},"keyword":"And ","text":"I entered College Name in sign up as '<College Name>'"},{"type":"Step","location":{"line":25,"column":1},"keyword":"And ","text":"I selected Sign Up Button in sign up"},{"type":"Step","location":{"line":26,"column":1},"keyword":"Then ","text":"verify content Signed up Successfully popup SMS in sign up as '<Signed up Successfully popup SMS>'"},{"type":"Step","location":{"line":27,"column":1},"keyword":"And ","text":"'<page>' is displayed with '<content>'"}],"scenario_tags":["@test"],"example":{"data":[{"key":"SlNo.","value":"1"},{"key":"First Name","value":"FirstName1"},{"key":"Last Name","value":"LastName1"},{"key":"Email Addresss","value":"EmailAddresss1"},{"key":"Passwords","value":"Passwords1"},{"key":"Confirm Password","value":"ConfirmPassword1"},{"key":"College Name","value":"CollegeName1"},{"key":"Signed up Successfully popup SMS","value":"SignedupSuccessfullypopupSMS1"},{"key":"page","value":"AlgoShack"},{"key":"content","value":"Sign In"}],"tags":[]}},"src/test/java/features/SAAS_Functional_TCs_Web Automation_SRS_TestCases_202306210730591.feature:57":{"file_name":"src/test/java/features/SAAS_Functional_TCs_Web Automation_SRS_TestCases_202306210730591.feature","location":{"line":1,"column":1},"feature_name":"SAAS_Functional_TCs_Web Automation_SRS_TestCases_202306210730591","scenario_name":"Try To create duplicate account then error message should be displayed saying user already exist","scenario_location":{"line":38,"column":1},"steps":[{"type":"Step","location":{"line":39,"column":1},"keyword":"Given ","text":"I have access to application"},{"type":"Step","location":{"line":40,"column":1},"keyword":"When ","text":"I selected Sign Up link in sign up"},{"type":"Step","location":{"line":41,"column":1},"keyword":"Then ","text":"verify displayed Sign Up to AlgoShack in sign up"},{"type":"Step","location":{"line":42,"column":1},"keyword":"When ","text":"I entered Existing First Name in sign up as '<Existing First Name1>'"},{"type":"Step","location":{"line":43,"column":1},"keyword":"And ","text":"I entered Existing Last Name in sign up as '<Existing Last Name2>'"},{"type":"Step","location":{"line":44,"column":1},"keyword":"And ","text":"I entered Existing Email Address in sign up as '<Existing Email Address3>'"},{"type":"Step","location":{"line":45,"column":1},"keyword":"And ","text":"I entered Existing Password in sign up as '<Existing Password4>'"},{"type":"Step","location":{"line":46,"column":1},"keyword":"And ","text":"I entered Existing Confirm Password in sign up as '<Existing Confirm Password5>'"},{"type":"Step","location":{"line":47,"column":1},"keyword":"And ","text":"I selected Are you a in sign up"},{"type":"Step","location":{"line":48,"column":1},"keyword":"And ","text":"I selected Company in sign up"},{"type":"Step","location":{"line":49,"column":1},"keyword":"And ","text":"I checked Terms And Agreement in sign up"},{"type":"Step","location":{"line":50,"column":1},"keyword":"And ","text":"I entered Company Name in sign up as '<Company Name>'"},{"type":"Step","location":{"line":51,"column":1},"keyword":"And ","text":"I selected Sign Up Button in sign up"},{"type":"Step","location":{"line":52,"column":1},"keyword":"Then ","text":"verify content User Already exists popup SMS in sign up as '<User Already exists popup SMS>'"},{"type":"Step","location":{"line":53,"column":1},"keyword":"And ","text":"'<page>' is displayed with '<content>'"}],"scenario_tags":["@test"],"example":{"data":[{"key":"SlNo.","value":"1"},{"key":"Existing First Name1","value":"ExistingFirstName1"},{"key":"Existing Last Name2","value":"ExistingLastName1"},{"key":"Existing Email Address3","value":"ExistingEmailAddress1"},{"key":"Existing Password4","value":"ExistingPassword1"},{"key":"Existing Confirm Password5","value":"ExistingConfirmPassword1"},{"key":"Company Name","value":"CompanyName1"},{"key":"User Already exists popup SMS","value":"UserAlreadyexistspopupSMS1"},{"key":"page","value":"AlgoShack"},{"key":"content","value":"Sign In"}],"tags":[]}},"src/test/java/features/SAAS_Functional_TCs_Web Automation_SRS_TestCases_202306210730591.feature:82":{"file_name":"src/test/java/features/SAAS_Functional_TCs_Web Automation_SRS_TestCases_202306210730591.feature","location":{"line":1,"column":1},"feature_name":"SAAS_Functional_TCs_Web Automation_SRS_TestCases_202306210730591","scenario_name":"Verify that user able to create an account without entering last name","scenario_location":{"line":64,"column":1},"steps":[{"type":"Step","location":{"line":65,"column":1},"keyword":"Given ","text":"I have access to application"},{"type":"Step","location":{"line":66,"column":1},"keyword":"When ","text":"I selected Sign Up link in sign up"},{"type":"Step","location":{"line":67,"column":1},"keyword":"Then ","text":"verify displayed Sign Up to AlgoShack in sign up"},{"type":"Step","location":{"line":68,"column":1},"keyword":"When ","text":"I entered First Name in sign up as '<First Name>'"},{"type":"Step","location":{"line":69,"column":1},"keyword":"And ","text":"I entered Email Addresss in sign up as '<Email Addresss>'"},{"type":"Step","location":{"line":70,"column":1},"keyword":"And ","text":"I entered Passwords in sign up as '<Passwords>'"},{"type":"Step","location":{"line":71,"column":1},"keyword":"And ","text":"I entered Confirm Password in sign up as '<Confirm Password>'"},{"type":"Step","location":{"line":72,"column":1},"keyword":"And ","text":"I selected Are you a in sign up"},{"type":"Step","location":{"line":73,"column":1},"keyword":"And ","text":"I selected Student in sign up"},{"type":"Step","location":{"line":74,"column":1},"keyword":"And ","text":"I checked Terms And Agreement in sign up"},{"type":"Step","location":{"line":75,"column":1},"keyword":"And ","text":"I entered College Name in sign up as '<College Name>'"},{"type":"Step","location":{"line":76,"column":1},"keyword":"And ","text":"I selected Sign Up Button in sign up"},{"type":"Step","location":{"line":77,"column":1},"keyword":"Then ","text":"verify content Signed up Successfully popup SMS in sign up as '<Signed up Successfully popup SMS>'"},{"type":"Step","location":{"line":78,"column":1},"keyword":"And ","text":"'<page>' is displayed with '<content>'"}],"scenario_tags":["@test"],"example":{"data":[{"key":"SlNo.","value":"1"},{"key":"First Name","value":"FirstName1"},{"key":"Email Addresss","value":"EmailAddresss1"},{"key":"Passwords","value":"Passwords1"},{"key":"Confirm Password","value":"ConfirmPassword1"},{"key":"College Name","value":"CollegeName1"},{"key":"Signed up Successfully popup SMS","value":"SignedupSuccessfullypopupSMS1"},{"key":"page","value":"AlgoShack"},{"key":"content","value":"Sign In"}],"tags":[]}},"src/test/java/features/SAAS_Functional_TCs_Web Automation_SRS_TestCases_202306210730591.feature:117":{"file_name":"src/test/java/features/SAAS_Functional_TCs_Web Automation_SRS_TestCases_202306210730591.feature","location":{"line":1,"column":1},"feature_name":"SAAS_Functional_TCs_Web Automation_SRS_TestCases_202306210730591","scenario_name":"An Account should not be created without First Name in SignUp Page","scenario_location":{"line":89,"column":1},"steps":[{"type":"Step","location":{"line":92,"column":1},"keyword":"Given ","text":"I have access to application"},{"type":"Step","location":{"line":93,"column":1},"keyword":"When ","text":"I selected Sign Up link in sign up"},{"type":"Step","location":{"line":94,"column":1},"keyword":"Then ","text":"verify displayed Sign Up to AlgoShack in sign up"},{"type":"Step","location":{"line":95,"column":1},"keyword":"When ","text":"I entered Last Name in sign up as '<Last Name>'"},{"type":"Step","location":{"line":96,"column":1},"keyword":"And ","text":"I clear text Email Addresss in sign up"},{"type":"Step","location":{"line":97,"column":1},"keyword":"And ","text":"I entered Passwords in sign up as '<Passwords>'"},{"type":"Step","location":{"line":98,"column":1},"keyword":"And ","text":"I entered Confirm Password in sign up as '<Confirm Password>'"},{"type":"Step","location":{"line":99,"column":1},"keyword":"And ","text":"I selected Are you a in sign up"},{"type":"Step","location":{"line":100,"column":1},"keyword":"And ","text":"I selected Student in sign up"},{"type":"Step","location":{"line":101,"column":1},"keyword":"And ","text":"I checked Terms And Agreement in sign up"},{"type":"Step","location":{"line":102,"column":1},"keyword":"And ","text":"I scroll and enter text College Name in sign up as '<College Name>'"},{"type":"Step","location":{"line":103,"column":1},"keyword":"And ","text":"I selected Sign Up Button in sign up"},{"type":"Step","location":{"line":104,"column":1},"keyword":"Then ","text":"verify content Please provide your first name error SMS in sign up as '<Please provide your first name error SMS>'"},{"type":"Step","location":{"line":105,"column":1},"keyword":"When ","text":"I scroll and enter text First Name in sign up as '<First Name>'"},{"type":"Step","location":{"line":106,"column":1},"keyword":"And ","text":"I scroll and enter text College Name in sign up as '<College Name1>'"},{"type":"Step","location":{"line":107,"column":1},"keyword":"And ","text":"I selected Sign Up Button in sign up"},{"type":"Step","location":{"line":108,"column":1},"keyword":"Then ","text":"verify content Please provide college name error SMS in sign up as '<Please provide college name error SMS>'"},{"type":"Step","location":{"line":109,"column":1},"keyword":"When ","text":"I clear text Email Addresss in sign up"},{"type":"Step","location":{"line":110,"column":1},"keyword":"And ","text":"I scroll and enter text College Name in sign up as '<College Name2>'"},{"type":"Step","location":{"line":111,"column":1},"keyword":"And ","text":"I selected Sign Up Button in sign up"},{"type":"Step","location":{"line":112,"column":1},"keyword":"Then ","text":"verify content Please provide your email address error SMS in sign up as '<Please provide your email address error SMS>'"},{"type":"Step","location":{"line":113,"column":1},"keyword":"And ","text":"'<page>' is displayed with '<content>'"}],"scenario_tags":["@test"],"example":{"data":[{"key":"SlNo.","value":"1"},{"key":"Last Name","value":"LastName1"},{"key":"Passwords","value":"Passwords1"},{"key":"Confirm Password","value":"ConfirmPassword1"},{"key":"College Name","value":"CollegeName1"},{"key":"Please provide your first name error SMS","value":"PleaseprovideyourfirstnameerrorSMS1"},{"key":"First Name","value":"FirstName1"},{"key":"College Name1","value":"CollegeName1"},{"key":"Please provide college name error SMS","value":"PleaseprovidecollegenameerrorSMS1"},{"key":"College Name2","value":"CollegeName1"},{"key":"Please provide your email address error SMS","value":"PleaseprovideyouremailaddresserrorSMS1"},{"key":"page","value":"AlgoShack"},{"key":"content","value":"Sign In"}],"tags":[]}},"src/test/java/features/SAAS_Functional_TCs_Web Automation_SRS_TestCases_202306210730591.feature:157":{"file_name":"src/test/java/features/SAAS_Functional_TCs_Web Automation_SRS_TestCases_202306210730591.feature","location":{"line":1,"column":1},"feature_name":"SAAS_Functional_TCs_Web Automation_SRS_TestCases_202306210730591","scenario_name":"In Sign Up Page verify the error SMS,When user enters Numbers in First Name and Last Name","scenario_location":{"line":124,"column":1},"steps":[{"type":"Step","location":{"line":128,"column":1},"keyword":"Given ","text":"I have access to application"},{"type":"Step","location":{"line":129,"column":1},"keyword":"When ","text":"I selected Sign Up link in sign up"},{"type":"Step","location":{"line":130,"column":1},"keyword":"Then ","text":"verify displayed Sign Up to AlgoShack in sign up"},{"type":"Step","location":{"line":131,"column":1},"keyword":"When ","text":"I entered First Name in sign up as '<First Name1>'"},{"type":"Step","location":{"line":132,"column":1},"keyword":"And ","text":"I entered Last Name in sign up as '<Last Name2>'"},{"type":"Step","location":{"line":133,"column":1},"keyword":"And ","text":"I entered Email Addresss in sign up as '<Email Addresss>'"},{"type":"Step","location":{"line":134,"column":1},"keyword":"And ","text":"I entered Passwords in sign up as '<Passwords>'"},{"type":"Step","location":{"line":135,"column":1},"keyword":"And ","text":"I entered Confirm Password in sign up as '<Confirm Password>'"},{"type":"Step","location":{"line":136,"column":1},"keyword":"And ","text":"I selected Are you a in sign up"},{"type":"Step","location":{"line":137,"column":1},"keyword":"And ","text":"I selected Student in sign up"},{"type":"Step","location":{"line":138,"column":1},"keyword":"And ","text":"I checked Terms And Agreement in sign up"},{"type":"Step","location":{"line":139,"column":1},"keyword":"And ","text":"I entered College Name in sign up as '<College Name>'"},{"type":"Step","location":{"line":140,"column":1},"keyword":"And ","text":"I selected Sign Up Button in sign up"},{"type":"Step","location":{"line":141,"column":1},"keyword":"Then ","text":"verify content Only alphabets are allowed for First name error SMS in sign up as '<Only alphabets are allowed for First name error SMS>'"},{"type":"Step","location":{"line":142,"column":1},"keyword":"And ","text":"verify content Only alphabets are allowed for Last name error SMS in sign up as '<Only alphabets are allowed for Last name error SMS>'"},{"type":"Step","location":{"line":143,"column":1},"keyword":"When ","text":"I clear and enter text First Name in sign up as '<First Name3>'"},{"type":"Step","location":{"line":144,"column":1},"keyword":"And ","text":"I clear and enter text Last Name in sign up as '<Last Name4>'"},{"type":"Step","location":{"line":145,"column":1},"keyword":"And ","text":"I selected Sign Up Button in sign up"},{"type":"Step","location":{"line":146,"column":1},"keyword":"Then ","text":"verify content Only alphabets are allowed for First name error SMS in sign up as '<Only alphabets are allowed for First name error SMS5>'"},{"type":"Step","location":{"line":147,"column":1},"keyword":"And ","text":"verify content Only alphabets are allowed for Last name error SMS in sign up as '<Only alphabets are allowed for Last name error SMS6>'"},{"type":"Step","location":{"line":148,"column":1},"keyword":"When ","text":"I clear and enter text First Name in sign up as '<First Name7>'"},{"type":"Step","location":{"line":149,"column":1},"keyword":"And ","text":"I clear and enter text Last Name in sign up as '<Last Name8>'"},{"type":"Step","location":{"line":150,"column":1},"keyword":"And ","text":"I selected Sign Up Button in sign up"},{"type":"Step","location":{"line":151,"column":1},"keyword":"Then ","text":"verify content Only alphabets are allowed for First name error SMS in sign up as '<Only alphabets are allowed for First name error SMS9>'"},{"type":"Step","location":{"line":152,"column":1},"keyword":"And ","text":"verify content Only alphabets are allowed for Last name error SMS in sign up as '<Only alphabets are allowed for Last name error SMS10>'"},{"type":"Step","location":{"line":153,"column":1},"keyword":"And ","text":"'<page>' is displayed with '<content>'"}],"scenario_tags":["@test"],"example":{"data":[{"key":"SlNo.","value":"1"},{"key":"First Name1","value":"FirstName2"},{"key":"Last Name2","value":"LastName2"},{"key":"Email Addresss","value":"EmailAddresss1"},{"key":"Passwords","value":"Passwords1"},{"key":"Confirm Password","value":"ConfirmPassword1"},{"key":"College Name","value":"CollegeName1"},{"key":"Only alphabets are allowed for First name error SMS","value":"OnlyalphabetsareallowedforFirstnameerrorSMS1"},{"key":"Only alphabets are allowed for Last name error SMS","value":"OnlyalphabetsareallowedforLastnameerrorSMS1"},{"key":"First Name3","value":"FirstName3"},{"key":"Last Name4","value":"LastName3"},{"key":"Only alphabets are allowed for First name error SMS5","value":"OnlyalphabetsareallowedforFirstnameerrorSMS1"},{"key":"Only alphabets are allowed for Last name error SMS6","value":"OnlyalphabetsareallowedforLastnameerrorSMS1"},{"key":"First Name7","value":"FirstName4"},{"key":"Last Name8","value":"LastName4"},{"key":"Only alphabets are allowed for First name error SMS9","value":"OnlyalphabetsareallowedforFirstnameerrorSMS1"},{"key":"Only alphabets are allowed for Last name error SMS10","value":"OnlyalphabetsareallowedforLastnameerrorSMS1"},{"key":"page","value":"AlgoShack"},{"key":"content","value":"Sign In"}],"tags":[]}},"src/test/java/features/SAAS_Functional_TCs_Web Automation_SRS_TestCases_202306210730591.feature:188":{"file_name":"src/test/java/features/SAAS_Functional_TCs_Web Automation_SRS_TestCases_202306210730591.feature","location":{"line":1,"column":1},"feature_name":"SAAS_Functional_TCs_Web Automation_SRS_TestCases_202306210730591","scenario_name":"In SignUp Page verify error message when password and confirm password is not entered","scenario_location":{"line":164,"column":1},"steps":[{"type":"Step","location":{"line":166,"column":1},"keyword":"Given ","text":"I have access to application"},{"type":"Step","location":{"line":167,"column":1},"keyword":"When ","text":"I selected Sign Up link in sign up"},{"type":"Step","location":{"line":168,"column":1},"keyword":"Then ","text":"verify displayed Sign Up to AlgoShack in sign up"},{"type":"Step","location":{"line":169,"column":1},"keyword":"When ","text":"I entered First Name in sign up as '<First Name>'"},{"type":"Step","location":{"line":170,"column":1},"keyword":"And ","text":"I entered Last Name in sign up as '<Last Name>'"},{"type":"Step","location":{"line":171,"column":1},"keyword":"And ","text":"I entered Email Addresss in sign up as '<Email Addresss>'"},{"type":"Step","location":{"line":172,"column":1},"keyword":"And ","text":"I selected Are you a in sign up"},{"type":"Step","location":{"line":173,"column":1},"keyword":"And ","text":"I selected Student in sign up"},{"type":"Step","location":{"line":174,"column":1},"keyword":"And ","text":"I checked Terms And Agreement in sign up"},{"type":"Step","location":{"line":175,"column":1},"keyword":"And ","text":"I entered College Name in sign up as '<College Name>'"},{"type":"Step","location":{"line":176,"column":1},"keyword":"And ","text":"I selected Sign Up Button in sign up"},{"type":"Step","location":{"line":177,"column":1},"keyword":"Then ","text":"verify content Please enter a password error SMS in sign up as '<Please enter a password error SMS>'"},{"type":"Step","location":{"line":178,"column":1},"keyword":"And ","text":"verify content Please enter a confirm password error SMS in sign up as '<Please enter a confirm password error SMS>'"},{"type":"Step","location":{"line":179,"column":1},"keyword":"When ","text":"I clear and enter text Email Addresss in sign up as '<Email Addresss1>'"},{"type":"Step","location":{"line":180,"column":1},"keyword":"And ","text":"I entered Passwords in sign up as '<Passwords>'"},{"type":"Step","location":{"line":181,"column":1},"keyword":"And ","text":"I entered Confirm Password in sign up as '<Confirm Password>'"},{"type":"Step","location":{"line":182,"column":1},"keyword":"And ","text":"I selected Sign Up Button in sign up"},{"type":"Step","location":{"line":183,"column":1},"keyword":"Then ","text":"verify content Please enter valid email address error SMS in sign up as '<Please enter valid email address error SMS>'"},{"type":"Step","location":{"line":184,"column":1},"keyword":"And ","text":"'<page>' is displayed with '<content>'"}],"scenario_tags":["@test"],"example":{"data":[{"key":"SlNo.","value":"1"},{"key":"First Name","value":"FirstName1"},{"key":"Last Name","value":"LastName1"},{"key":"Email Addresss","value":"EmailAddresss1"},{"key":"College Name","value":"CollegeName1"},{"key":"Please enter a password error SMS","value":"PleaseenterapassworderrorSMS1"},{"key":"Please enter a confirm password error SMS","value":"PleaseenteraconfirmpassworderrorSMS1"},{"key":"Email Addresss1","value":"EmailAddresss2"},{"key":"Passwords","value":"Passwords1"},{"key":"Confirm Password","value":"ConfirmPassword1"},{"key":"Please enter valid email address error SMS","value":"PleaseentervalidemailaddresserrorSMS1"},{"key":"page","value":"AlgoShack"},{"key":"content","value":"Sign In"}],"tags":[]}},"src/test/java/features/SAAS_Functional_TCs_Web Automation_SRS_TestCases_202306210730591.feature:226":{"file_name":"src/test/java/features/SAAS_Functional_TCs_Web Automation_SRS_TestCases_202306210730591.feature","location":{"line":1,"column":1},"feature_name":"SAAS_Functional_TCs_Web Automation_SRS_TestCases_202306210730591","scenario_name":"User should verify error message when passing All Uppercase letter in the Password in SignUp Page","scenario_location":{"line":195,"column":1},"steps":[{"type":"Step","location":{"line":199,"column":1},"keyword":"Given ","text":"I have access to application"},{"type":"Step","location":{"line":200,"column":1},"keyword":"When ","text":"I selected Sign Up link in sign up"},{"type":"Step","location":{"line":201,"column":1},"keyword":"Then ","text":"verify displayed Sign Up to AlgoShack in sign up"},{"type":"Step","location":{"line":202,"column":1},"keyword":"When ","text":"I entered First Name in sign up as '<First Name>'"},{"type":"Step","location":{"line":203,"column":1},"keyword":"And ","text":"I entered Last Name in sign up as '<Last Name>'"},{"type":"Step","location":{"line":204,"column":1},"keyword":"And ","text":"I entered Email Addresss in sign up as '<Email Addresss>'"},{"type":"Step","location":{"line":205,"column":1},"keyword":"And ","text":"I entered Passwords in sign up as '<Passwords1>'"},{"type":"Step","location":{"line":206,"column":1},"keyword":"And ","text":"I entered Confirm Password in sign up as '<Confirm Password>'"},{"type":"Step","location":{"line":207,"column":1},"keyword":"And ","text":"I selected Are you a in sign up"},{"type":"Step","location":{"line":208,"column":1},"keyword":"And ","text":"I selected Student in sign up"},{"type":"Step","location":{"line":209,"column":1},"keyword":"And ","text":"I checked Terms And Agreement in sign up"},{"type":"Step","location":{"line":210,"column":1},"keyword":"And ","text":"I entered College Name in sign up as '<College Name>'"},{"type":"Step","location":{"line":211,"column":1},"keyword":"And ","text":"I selected Sign Up Button in sign up"},{"type":"Step","location":{"line":212,"column":1},"keyword":"Then ","text":"verify content Invalid password error SMS in sign up as '<Invalid password error SMS2>'"},{"type":"Step","location":{"line":213,"column":1},"keyword":"When ","text":"I clear and enter text Passwords in sign up as '<Passwords3>'"},{"type":"Step","location":{"line":214,"column":1},"keyword":"And ","text":"I selected Sign Up Button in sign up"},{"type":"Step","location":{"line":215,"column":1},"keyword":"Then ","text":"verify content Invalid password error SMS in sign up as '<Invalid password error SMS4>'"},{"type":"Step","location":{"line":216,"column":1},"keyword":"When ","text":"I clear and enter text Passwords in sign up as '<Passwords5>'"},{"type":"Step","location":{"line":217,"column":1},"keyword":"And ","text":"I selected Sign Up Button in sign up"},{"type":"Step","location":{"line":218,"column":1},"keyword":"Then ","text":"verify content Invalid password error SMS in sign up as '<Invalid password error SMS6>'"},{"type":"Step","location":{"line":219,"column":1},"keyword":"When ","text":"I clear and enter text Passwords in sign up as '<Passwords7>'"},{"type":"Step","location":{"line":220,"column":1},"keyword":"And ","text":"I selected Sign Up Button in sign up"},{"type":"Step","location":{"line":221,"column":1},"keyword":"Then ","text":"verify content Invalid password error SMS in sign up as '<Invalid password error SMS8>'"},{"type":"Step","location":{"line":222,"column":1},"keyword":"And ","text":"'<page>' is displayed with '<content>'"}],"scenario_tags":["@test"],"example":{"data":[{"key":"SlNo.","value":"1"},{"key":"First Name","value":"FirstName1"},{"key":"Last Name","value":"LastName1"},{"key":"Email Addresss","value":"EmailAddresss1"},{"key":"Passwords1","value":"Passwords2"},{"key":"Confirm Password","value":"ConfirmPassword1"},{"key":"College Name","value":"CollegeName1"},{"key":"Invalid password error SMS2","value":"InvalidpassworderrorSMS1"},{"key":"Passwords3","value":"Passwords3"},{"key":"Invalid password error SMS4","value":"InvalidpassworderrorSMS1"},{"key":"Passwords5","value":"Passwords4"},{"key":"Invalid password error SMS6","value":"InvalidpassworderrorSMS1"},{"key":"Passwords7","value":"Passwords5"},{"key":"Invalid password error SMS8","value":"InvalidpassworderrorSMS1"},{"key":"page","value":"AlgoShack"},{"key":"content","value":"Sign In"}],"tags":[]}},"src/test/java/features/SAAS_Functional_TCs_Web Automation_SRS_TestCases_202306210730591.feature:2658":{"file_name":"src/test/java/features/SAAS_Functional_TCs_Web Automation_SRS_TestCases_202306210730591.feature","location":{"line":1,"column":1},"feature_name":"SAAS_Functional_TCs_Web Automation_SRS_TestCases_202306210730591","scenario_name":"select the No of pages from Row of Pages and verify the displayed scenarios in the page","scenario_location":{"line":2624,"column":1},"steps":[{"type":"Step","location":{"line":2625,"column":1},"keyword":"Given ","text":"I have access to application"},{"type":"Step","location":{"line":2626,"column":1},"keyword":"When ","text":"I Clicked SignIn link in sign in"},{"type":"Step","location":{"line":2627,"column":1},"keyword":"Then ","text":"verify displayed Sign In to AlgoShack in sign in"},{"type":"Step","location":{"line":2628,"column":1},"keyword":"When ","text":"I entered Email Address in sign in as '<Email Address>'"},{"type":"Step","location":{"line":2629,"column":1},"keyword":"And ","text":"I entered Password in sign in as '<Password>'"},{"type":"Step","location":{"line":2630,"column":1},"keyword":"And ","text":"I Clicked Sign In Button in sign in"},{"type":"Step","location":{"line":2631,"column":1},"keyword":"Then ","text":"verify content User Signed In Successfully in sign in as '<User Signed In Successfully>'"},{"type":"Step","location":{"line":2632,"column":1},"keyword":"And ","text":"verify displayed Home Page in home page"},{"type":"Step","location":{"line":2633,"column":1},"keyword":"When ","text":"I Clicked algoQA in home page"},{"type":"Step","location":{"line":2634,"column":1},"keyword":"And ","text":"I Clicked algoProfiler in home page"},{"type":"Step","location":{"line":2635,"column":1},"keyword":"Then ","text":"verify displayed Project Explorer Label in project explorer"},{"type":"Step","location":{"line":2636,"column":1},"keyword":"When ","text":"I entered Search Project name in project explorer as '<Search Project name1>'"},{"type":"Step","location":{"line":2637,"column":1},"keyword":"And ","text":"I selected Existing Project in project explorer"},{"type":"Step","location":{"line":2638,"column":1},"keyword":"Then ","text":"verify displayed Canvas Page in canvas"},{"type":"Step","location":{"line":2639,"column":1},"keyword":"When ","text":"I selected More in canvas"},{"type":"Step","location":{"line":2640,"column":1},"keyword":"And ","text":"I selected Edit Scenarios in more"},{"type":"Step","location":{"line":2641,"column":1},"keyword":"Then ","text":"verify displayed Edit Scenario Form label in edit scenarios"},{"type":"Step","location":{"line":2642,"column":1},"keyword":"When ","text":"I selected Rows per page in edit scenarios"},{"type":"Step","location":{"line":2643,"column":1},"keyword":"And ","text":"I selected Rows per page as in edit scenarios as '<Rows per page as2>'"},{"type":"Step","location":{"line":2644,"column":1},"keyword":"Then ","text":"verify displayed No of scenarios in the page as 5 in edit scenarios"},{"type":"Step","location":{"line":2645,"column":1},"keyword":"When ","text":"I selected Rows per page in edit scenarios"},{"type":"Step","location":{"line":2646,"column":1},"keyword":"And ","text":"I selected Rows per page as in edit scenarios as '<Rows per page as3>'"},{"type":"Step","location":{"line":2647,"column":1},"keyword":"Then ","text":"verify displayed No of scenarios in the page as 10 in edit scenarios"},{"type":"Step","location":{"line":2648,"column":1},"keyword":"When ","text":"I selected Rows per page in edit scenarios"},{"type":"Step","location":{"line":2649,"column":1},"keyword":"And ","text":"I selected Rows per page as in edit scenarios as '<Rows per page as4>'"},{"type":"Step","location":{"line":2650,"column":1},"keyword":"Then ","text":"verify displayed No of scenarios in the page as 25 in edit scenarios"},{"type":"Step","location":{"line":2651,"column":1},"keyword":"When ","text":"I selected Rows per page in edit scenarios"},{"type":"Step","location":{"line":2652,"column":1},"keyword":"And ","text":"I selected Rows per page as in edit scenarios as '<Rows per page as5>'"},{"type":"Step","location":{"line":2653,"column":1},"keyword":"Then ","text":"verify displayed No of scenarios in the page as All in edit scenarios"},{"type":"Step","location":{"line":2654,"column":1},"keyword":"And ","text":"'<page>' is displayed with '<content>'"}],"scenario_tags":["@Checking_the_pagination","@uida941116880","@set21","@test064","@EditScenarios"],"example":{"data":[{"key":"SlNo.","value":"1"},{"key":"Email Address","value":"EmailAddress1"},{"key":"Password","value":"Password1"},{"key":"User Signed In Successfully","value":"UserSignedInSuccessfully1"},{"key":"Search Project name1","value":"SearchProjectname2"},{"key":"Rows per page as2","value":"Rowsperpageas1"},{"key":"Rows per page as3","value":"Rowsperpageas2"},{"key":"Rows per page as4","value":"Rowsperpageas3"},{"key":"Rows per page as5","value":"Rowsperpageas4"},{"key":"page","value":"AlgoShack"},{"key":"content","value":"algoQA"}],"tags":[]}}}